system_metrics_easy/__init__.py
system_metrics_easy/server_metrics.py
system_metrics_easy-1.3.2.dist-info/licenses/LICENSE
system_metrics_easy-1.3.2.dist-info/METADATA
system_metrics_easy-1.3.2.dist-info/WHEEL
system_metrics_easy-1.3.2.dist-info/entry_points.txt
system_metrics_easy-1.3.2.dist-info/top_level.txt
system_metrics_easy-1.3.2.dist-info/RECORD
