Metadata-Version: 2.4
Name: system-metrics-easy
Version: 1.3.2
Summary: A comprehensive server monitoring tool that collects and sends system metrics to a Socket.IO server
Home-page: https://github.com/hamzaig/system-metrics-easy
Author: Moonsys
Author-email: Moonsys <admin@moonsys.co>
License: MIT
Project-URL: Homepage, https://github.com/hamzaig/system-metrics-easy
Project-URL: Repository, https://github.com/hamzaig/system-metrics-easy
Project-URL: Issues, https://github.com/hamzaig/system-metrics-easy/issues
Project-URL: Documentation, https://github.com/hamzaig/system-metrics-easy#readme
Keywords: server,monitoring,metrics,system,stats,cpu,memory,disk,network,gpu,socketio
Classifier: Development Status :: 5 - Production/Stable
Classifier: Intended Audience :: System Administrators
Classifier: Intended Audience :: Developers
Classifier: License :: OSI Approved :: MIT License
Classifier: Operating System :: OS Independent
Classifier: Programming Language :: Python :: 3
Classifier: Programming Language :: Python :: 3.8
Classifier: Programming Language :: Python :: 3.9
Classifier: Programming Language :: Python :: 3.10
Classifier: Programming Language :: Python :: 3.11
Classifier: Programming Language :: Python :: 3.12
Classifier: Topic :: System :: Monitoring
Classifier: Topic :: System :: Systems Administration
Classifier: Topic :: Software Development :: Libraries :: Python Modules
Requires-Python: >=3.8
License-File: LICENSE
Requires-Dist: bidict==0.23.1
Requires-Dist: certifi==2025.8.3
Requires-Dist: charset-normalizer==3.4.3
Requires-Dist: python-dotenv==1.1.1
Requires-Dist: h11==0.16.0
Requires-Dist: idna==3.10
Requires-Dist: psutil==7.1.0
Requires-Dist: python-engineio==4.12.2
Requires-Dist: python-socketio==5.13.0
Requires-Dist: requests==2.32.5
Requires-Dist: simple-websocket==1.1.0
Requires-Dist: urllib3==2.5.0
Requires-Dist: websocket-client>=1.0.0
Requires-Dist: wsproto==1.2.0
Dynamic: author
Dynamic: home-page
Dynamic: license-file
Dynamic: requires-python
